Metadata-Version: 1.1
Name: securefile-handler
Version: 0.1.2
Summary: Module for secure (re)moving files and folders with content
Home-page: https://github.com/dvorakj31/securefile_handler
Author: Jakub Dvořák
Author-email: dvoraj84@fit.cvut.cz
License: MIT
Keywords: python module secure file content remove shred move
Platform: UNKNOWN
Classifier: Intended Audience :: Developers
Classifier: Intended Audience :: Education
Classifier: License :: OSI Approved :: MIT License
Classifier: Programming Language :: Cython
Classifier: Programming Language :: Python
Classifier: Programming Language :: Python :: Implementation :: CPython
Classifier: Programming Language :: Python :: 3
Classifier: Programming Language :: Python :: 3.6
Classifier: Programming Language :: Python :: 3.7
Classifier: Topic :: Software Development :: Libraries :: Python Modules
Classifier: Topic :: Utilities
